leetcode_cracker/__init__.py
leetcode_cracker/question_1.py
leetcode_cracker/question_1137.py
leetcode_cracker/question_118.py
leetcode_cracker/question_119.py
leetcode_cracker/question_121.py
leetcode_cracker/question_1480.py
leetcode_cracker/question_169.py
leetcode_cracker/question_217.py
leetcode_cracker/question_22.py
leetcode_cracker/question_2235.py
leetcode_cracker/question_231.py
leetcode_cracker/question_2469.py
leetcode_cracker/question_258.py
leetcode_cracker/question_263.py
leetcode_cracker/question_268.py
leetcode_cracker/question_278.py
leetcode_cracker/question_283.py
leetcode_cracker/question_326.py
leetcode_cracker/question_342.py
leetcode_cracker/question_35.py
leetcode_cracker/question_367.py
leetcode_cracker/question_371.py
leetcode_cracker/question_392.py
leetcode_cracker/question_415.py
leetcode_cracker/question_43.py
leetcode_cracker/question_46.py
leetcode_cracker/question_47.py
leetcode_cracker/question_50.py
leetcode_cracker/question_509.py
leetcode_cracker/question_58.py
leetcode_cracker/question_66.py
leetcode_cracker/question_67.py
leetcode_cracker/question_70.py
leetcode_cracker/question_728.py
leetcode_cracker/question_9.py
leetcode_cracker/utils.py
leetcode_cracker-0.0.5.dist-info/LICENSE
leetcode_cracker-0.0.5.dist-info/METADATA
leetcode_cracker-0.0.5.dist-info/WHEEL
leetcode_cracker-0.0.5.dist-info/top_level.txt
leetcode_cracker-0.0.5.dist-info/RECORD
