Metadata-Version: 2.1
Name: leetcode-cracker
Version: 0.0.5
Summary: package to assist in solving Leetcode Problems
Author-email: Albert <albertyqyao@gmail.com>
Project-URL: Homepage, https://github.com/AlbertY123/leetcode-cracker
Classifier: Programming Language :: Python :: 3
Classifier: License :: OSI Approved :: MIT License
Classifier: Operating System :: OS Independent
Requires-Python: >=3.10
License-File: LICENSE
